kvprocessor/__init__.py
kvprocessor/cli.py
kvprocessor/kvdiff.py
kvprocessor/kvenvloader.py
kvprocessor/kvfileexporter.py
kvprocessor/kvfilemerger.py
kvprocessor/kvfileutils.py
kvprocessor/kvglobalsettings.py
kvprocessor/kvmanifestloader.py
kvprocessor/kvnamespacemanager.py
kvprocessor/kvprocessor.py
kvprocessor/kvstructloader.py
kvprocessor/kvtypemap.py
kvprocessor/kvvalidator.py
kvprocessor/kvversionmanager.py
kvprocessor/util/errors.py
kvprocessor/util/filedownloader.py
kvprocessor/util/log.py
kvprocessor/util/warnings.py
kvprocessor-0.2.14.dist-info/METADATA
kvprocessor-0.2.14.dist-info/WHEEL
kvprocessor-0.2.14.dist-info/licenses/LICENSE
kvprocessor-0.2.14.dist-info/RECORD
