Metadata-Version: 2.4
Name: kvprocessor
Version: 0.2.14
Summary: A Python package for processing and validating configuration dictionaries against a custom .kv file format
Project-URL: Homepage, https://github.com/connor33341/kvprocessor
Project-URL: Repository, https://github.com/connor33341/kvprocessor
Author-email: connor33341 <connor@connor33341.dev>
License: MIT License
License-File: LICENSE
Classifier: License :: OSI Approved :: MIT License
Classifier: Programming Language :: Python :: 3
Classifier: Programming Language :: Python :: 3.8
Classifier: Programming Language :: Python :: 3.9
Classifier: Programming Language :: Python :: 3.10
Classifier: Programming Language :: Python :: 3.11
Requires-Python: >=3.9
Requires-Dist: requests>=2.25.0
